validx/__init__.py
validx/contracts.py
validx/platform.py
validx/py.typed
validx/cy/__init__.py
validx/cy/abstract.pxd
validx/cy/abstract.pyi
validx/cy/abstract.pyx
validx/cy/bools.pyi
validx/cy/bools.pyx
validx/cy/chars.pyi
validx/cy/chars.pyx
validx/cy/classes.pxd
validx/cy/classes.pyi
validx/cy/classes.pyx
validx/cy/containers.pyi
validx/cy/containers.pyx
validx/cy/datetimes.pyi
validx/cy/datetimes.pyx
validx/cy/instances.pxd
validx/cy/instances.pyi
validx/cy/instances.pyx
validx/cy/numbers.pyi
validx/cy/numbers.pyx
validx/cy/pipelines.pyi
validx/cy/pipelines.pyx
validx/cy/special.pyi
validx/cy/special.pyx
validx/exc/__init__.py
validx/exc/errors.py
validx/exc/errors.pyi
validx/exc/formatter.py
validx/exc/formatter.pyi
validx/exc/markers.py
validx/exc/markers.pyi
validx/py/__init__.py
validx/py/abstract.py
validx/py/abstract.pyi
validx/py/bools.py
validx/py/bools.pyi
validx/py/chars.py
validx/py/chars.pyi
validx/py/classes.py
validx/py/classes.pyi
validx/py/containers.py
validx/py/containers.pyi
validx/py/datetimes.py
validx/py/datetimes.pyi
validx/py/instances.py
validx/py/instances.pyi
validx/py/numbers.py
validx/py/numbers.pyi
validx/py/pipelines.py
validx/py/pipelines.pyi
validx/py/special.py
validx/py/special.pyi
ValidX-0.8.1.dist-info/LICENCE.txt
ValidX-0.8.1.dist-info/METADATA
ValidX-0.8.1.dist-info/WHEEL
ValidX-0.8.1.dist-info/top_level.txt
ValidX-0.8.1.dist-info/RECORD
