Metadata-Version: 2.1
Name: ValidX
Version: 0.8.1
Summary: fast, powerful, and flexible validator with sane syntax
Home-page: https://github.com/Cottonwood-Technology/ValidX
Author: Cottonwood Technology
Author-email: info@cottonwood.tech
License: BSD
Keywords: validator validation validate schema
Platform: UNKNOWN
Classifier: Intended Audience :: Developers
Classifier: License :: OSI Approved :: BSD License
Classifier: Programming Language :: Cython
Classifier: Programming Language :: Python
Classifier: Programming Language :: Python :: 3.6
Classifier: Programming Language :: Python :: 3.7
Classifier: Programming Language :: Python :: 3.8
Classifier: Programming Language :: Python :: 3.9
Classifier: Programming Language :: Python :: 3.10
Classifier: Programming Language :: Python :: 3.11
Classifier: Programming Language :: Python :: Implementation :: CPython
Classifier: Programming Language :: Python :: Implementation :: PyPy
Classifier: Development Status :: 5 - Production/Stable
Requires-Python: >=3.6
